spikezoo/__init__.py
spikezoo/archs/__init__.py
spikezoo/archs/__pycache__/__init__.cpython-39.pyc
spikezoo/archs/base/nets.py
spikezoo/archs/base/__pycache__/nets.cpython-39.pyc
spikezoo/archs/bsf/README.md
spikezoo/archs/bsf/main.py
spikezoo/archs/bsf/requirements.txt
spikezoo/archs/bsf/test.py
spikezoo/archs/bsf/utils.py
spikezoo/archs/bsf/datasets/datasets.py
spikezoo/archs/bsf/datasets/ds_utils.py
spikezoo/archs/bsf/metrics/psnr.py
spikezoo/archs/bsf/metrics/ssim.py
spikezoo/archs/bsf/models/get_model.py
spikezoo/archs/bsf/models/bsf/align.py
spikezoo/archs/bsf/models/bsf/bsf.py
spikezoo/archs/bsf/models/bsf/dsft_convert.py
spikezoo/archs/bsf/models/bsf/rep.py
spikezoo/archs/bsf/models/bsf/__pycache__/align.cpython-39.pyc
spikezoo/archs/bsf/models/bsf/__pycache__/bsf.cpython-39.pyc
spikezoo/archs/bsf/models/bsf/__pycache__/rep.cpython-39.pyc
spikezoo/archs/bsf/prepare_data/DSFT.py
spikezoo/archs/bsf/prepare_data/crop_dataset_train.py
spikezoo/archs/bsf/prepare_data/crop_dataset_val.py
spikezoo/archs/bsf/prepare_data/crop_train.sh
spikezoo/archs/bsf/prepare_data/crop_val.sh
spikezoo/archs/bsf/prepare_data/io_utils.py
spikezoo/archs/spikeclip/nets.py
spikezoo/archs/spikeclip/__pycache__/nets.cpython-39.pyc
spikezoo/archs/spk2imgnet/.gitignore
spikezoo/archs/spk2imgnet/DCNv2.py
spikezoo/archs/spk2imgnet/align_arch.py
spikezoo/archs/spk2imgnet/dataset.py
spikezoo/archs/spk2imgnet/nets.py
spikezoo/archs/spk2imgnet/readme.md
spikezoo/archs/spk2imgnet/test_gen_imgseq.py
spikezoo/archs/spk2imgnet/train.py
spikezoo/archs/spk2imgnet/utils.py
spikezoo/archs/spk2imgnet/.github/workflows/pylint.yml
spikezoo/archs/spk2imgnet/__pycache__/DCNv2.cpython-39.pyc
spikezoo/archs/spk2imgnet/__pycache__/align_arch.cpython-39.pyc
spikezoo/archs/spk2imgnet/__pycache__/nets.cpython-39.pyc
spikezoo/archs/ssir/README.md
spikezoo/archs/ssir/losses.py
spikezoo/archs/ssir/main.py
spikezoo/archs/ssir/requirements.txt
spikezoo/archs/ssir/test.py
spikezoo/archs/ssir/utils.py
spikezoo/archs/stir/package_core/package_core.egg-info/PKG-INFO
spikezoo/archs/stir/package_core/package_core.egg-info/SOURCES.txt
spikezoo/archs/stir/package_core/package_core.egg-info/dependency_links.txt
spikezoo/archs/stir/package_core/package_core.egg-info/top_level.txt
spikezoo-0.2.3.7.dist-info/LICENSE.txt
spikezoo-0.2.3.7.dist-info/METADATA
spikezoo-0.2.3.7.dist-info/WHEEL
spikezoo-0.2.3.7.dist-info/top_level.txt
spikezoo-0.2.3.7.dist-info/RECORD
