Metadata-Version: 2.2
Name: spikezoo
Version: 0.2.3.7
Summary: A deep learning toolbox for spike-to-image models.
Home-page: https://github.com/chenkang455/Spike-Zoo
Author: Kang Chen
Author-email: mrchenkang@stu.pku.edu.cn
Requires-Python: >=3.7
License-File: LICENSE.txt
Requires-Dist: torch
Requires-Dist: requests
Requires-Dist: numpy
Requires-Dist: tqdm
Requires-Dist: scikit-image
Requires-Dist: lpips
Requires-Dist: pyiqa
Requires-Dist: opencv-python
Requires-Dist: thop
Requires-Dist: pytorch-wavelets
Requires-Dist: pytz
Requires-Dist: PyWavelets
Requires-Dist: pandas
Requires-Dist: pillow
Requires-Dist: scikit-learn
Requires-Dist: scipy
Requires-Dist: spikingjelly
Requires-Dist: setuptools
Dynamic: author
Dynamic: author-email
Dynamic: description
Dynamic: description-content-type
Dynamic: home-page
Dynamic: requires-dist
Dynamic: requires-python
Dynamic: summary
